Fibonacci/Qvizi.py
Fibonacci/__init__.py
FibonacciTsiklauri-0.0.1.dist-info/LICENSE.txt
FibonacciTsiklauri-0.0.1.dist-info/METADATA
FibonacciTsiklauri-0.0.1.dist-info/WHEEL
FibonacciTsiklauri-0.0.1.dist-info/top_level.txt
FibonacciTsiklauri-0.0.1.dist-info/RECORD
