Metadata-Version: 2.1
Name: FibonacciTsiklauri
Version: 0.0.1
Summary: Fibonacci Sequence
Author: tsikla
Author-email: tsotne.tsiklauri.1@btu.edu.ge
Classifier: Programming Language :: Python :: 3
Classifier: License :: OSI Approved :: MIT License
Classifier: Operating System :: OS Independent
Requires-Python: >=3.6
License-File: LICENSE.txt
